lamar_unused_assets_report/__init__.py
lamar_unused_assets_report/main.py
lamar_unused_assets_report-1.0.0.dist-info/METADATA
lamar_unused_assets_report-1.0.0.dist-info/WHEEL
lamar_unused_assets_report-1.0.0.dist-info/entry_points.txt
lamar_unused_assets_report-1.0.0.dist-info/top_level.txt
lamar_unused_assets_report-1.0.0.dist-info/RECORD
