Metadata-Version: 2.4
Name: lamar-unused-assets-report
Version: 1.0.0
Summary: Generate a CSV report for unused CMS assets from Lamar's API.
Home-page: https://github.com/yourusername/lamar-unused-assets-report
Author: Your Name
Author-email: your.email@example.com
Classifier: Programming Language :: Python :: 3
Classifier: License :: OSI Approved :: MIT License
Classifier: Operating System :: OS Independent
Requires-Python: >=3.7
Requires-Dist: requests
Dynamic: author
Dynamic: author-email
Dynamic: classifier
Dynamic: description
Dynamic: description-content-type
Dynamic: home-page
Dynamic: requires-dist
Dynamic: requires-python
Dynamic: summary
